mathcore/__init__.py
mathcore/base_converter.py
mathcore/constants.py
mathcore/errors.py
mathcore/function_evaluator.py
mathcore/functions.py
mathcore/parser.py
mathcore/plotter.py
mathcore/safe_eval.py
mathcore/solver.py
mathcore/value_table.py
grapho_mathcore-0.1.0.dist-info/METADATA
grapho_mathcore-0.1.0.dist-info/WHEEL
grapho_mathcore-0.1.0.dist-info/top_level.txt
grapho_mathcore-0.1.0.dist-info/RECORD
