Metadata-Version: 2.4
Name: grapho-mathcore
Version: 0.1.0
Summary: Safe mathematical evaluation and utilities
Author: Lynx
License: MIT
Requires-Python: >=3.1
